lo_extension_dev/__init__.py
lo_extension_dev/addons.py
lo_extension_dev/addons.yml
lo_extension_dev/extension.yml
lo_extension_dev/manage.py
lo_extension_dev-0.0.6.dist-info/METADATA
lo_extension_dev-0.0.6.dist-info/WHEEL
lo_extension_dev-0.0.6.dist-info/entry_points.txt
lo_extension_dev-0.0.6.dist-info/licenses/LICENSE.txt
lo_extension_dev-0.0.6.dist-info/RECORD
