Metadata-Version: 2.1
Name: lo-extension-dev
Version: 0.0.6
Summary: A tool to help developing LibreOffice Extension.
Project-URL: Bug Reports, https://github.com/bastien34/lo-extension-dev/issues
Project-URL: Source, https://github.com/bastien34/lo-extension-dev
License: Copyright (c) 2023-Bastien Roques
License-File: LICENSE.txt
Keywords: development,extension,libreoffice
Classifier: Programming Language :: Python :: 3 :: Only
Classifier: Programming Language :: Python :: 3.7
Classifier: Programming Language :: Python :: 3.8
Classifier: Programming Language :: Python :: 3.9
Classifier: Programming Language :: Python :: 3.10
Classifier: Programming Language :: Python :: 3.11
Requires-Python: >=3.7
Requires-Dist: argparse
Requires-Dist: psutil
Requires-Dist: pyyaml
